celpy/__init__.py
celpy/__main__.py
celpy/adapter.py
celpy/c7nlib.py
celpy/cel.lark
celpy/celparser.py
celpy/celtypes.py
celpy/evaluation.py
celpy/py.typed
cel_python-0.4.0.dist-info/METADATA
cel_python-0.4.0.dist-info/WHEEL
cel_python-0.4.0.dist-info/entry_points.txt
cel_python-0.4.0.dist-info/licenses/LICENSE
cel_python-0.4.0.dist-info/RECORD
