Metadata-Version: 2.4
Name: cel-python
Version: 0.4.0
Summary: Pure Python implementation of Google Common Expression Language
Author-email: "S.Lott" <slott56@gmail.com>
License-File: LICENSE
Classifier: Development Status :: 4 - Beta
Classifier: Programming Language :: Python
Requires-Python: >=3.9
Requires-Dist: google-re2>=1.1.20240702; python_version != '3.13' or sys_platform != 'darwin' or platform_machine != 'arm64'
Requires-Dist: jmespath>=1.0.1
Requires-Dist: lark>=1.2.2
Requires-Dist: pendulum>=3.1.0
Requires-Dist: pyyaml>=6.0.2
Requires-Dist: tomli>=1.1.0; python_version < '3.11'
